amr_io.py
doc_amr.py
docSmatch/__init__.py
docSmatch/amr.py
docSmatch/smatch.py
doc_amr_baseline/__init__.py
doc_amr_baseline/amr_constituents.py
doc_amr_baseline/baseline_io.py
doc_amr_baseline/get_allen_coref.py
doc_amr_baseline/make_doc_amr.py
docAMR-0.1.1.dist-info/LICENSE
docAMR-0.1.1.dist-info/METADATA
docAMR-0.1.1.dist-info/WHEEL
docAMR-0.1.1.dist-info/entry_points.txt
docAMR-0.1.1.dist-info/top_level.txt
docAMR-0.1.1.dist-info/RECORD
