Metadata-Version: 2.1
Name: docAMR
Version: 0.1.1
Summary: The package for docAMR
Author-email: Sadhana <sadhana.kumaravel1@ibm.com>, Tahira <tnaseem@us.ibm.com>, GX <GX.Xu@ibm.com>
Project-URL: Homepage, https://github.com/IBM/docAMR
Project-URL: Bug Tracker, https://github.com/IBM/docAMR/issues
Classifier: Programming Language :: Python :: 3
Classifier: License :: OSI Approved :: Apache Software License
Classifier: Operating System :: POSIX :: Linux
Requires-Python: ~=3.8
License-File: LICENSE
Requires-Dist: tqdm
Requires-Dist: penman
Requires-Dist: ipdb
